msAI/__init__.py
msAI/__main__.py
msAI/errors.py
msAI/metadata.py
msAI/miscDecos.py
msAI/miscUtils.py
msAI/msData.py
msAI/samples.py
msAI/types.py
msAI-1.3.1.dev0.dist-info/METADATA
msAI-1.3.1.dev0.dist-info/WHEEL
msAI-1.3.1.dev0.dist-info/top_level.txt
msAI-1.3.1.dev0.dist-info/RECORD
