Metadata-Version: 2.1
Name: msAI
Version: 1.3.1.dev0
Summary: Tools to create AI models for mass spectrometry data
Home-page: https://github.com/IsotopeC/msAI
Author: Calvin Peters
Author-email: calvin.isotope@gmail.com
License: UNKNOWN
Keywords: AI models mass spectrometry MS data mzML spectrum ion chromatogram TIC extracted-ion EIC XIC machine learning artificial intelligence deep neural network
Platform: UNKNOWN
Classifier: Programming Language :: Python :: 3
Classifier: Operating System :: OS Independent
Classifier: Topic :: Scientific/Engineering :: Artificial Intelligence
Classifier: Topic :: Scientific/Engineering :: Bio-Informatics
Classifier: Topic :: Scientific/Engineering :: Chemistry
Classifier: Topic :: Scientific/Engineering :: Mathematics
Classifier: Topic :: Scientific/Engineering :: Visualization
Requires-Python: >3.6
Requires-Dist: numpy
Requires-Dist: pandas
Requires-Dist: tensorflow
Requires-Dist: pymzml
